whitespace_format.py
whitespace_format-0.0.15.dist-info/LICENSE
whitespace_format-0.0.15.dist-info/METADATA
whitespace_format-0.0.15.dist-info/WHEEL
whitespace_format-0.0.15.dist-info/entry_points.txt
whitespace_format-0.0.15.dist-info/RECORD
