Metadata-Version: 2.3
Name: whitespace-format
Version: 0.0.15
Summary: Linter and formatter of whitespace in source code files and text files
License: MIT
Author: David Pal
Author-email: davidko.pal@gmail.com
Requires-Python: >=3.8.0,<4.0.0
Classifier: License :: OSI Approved :: MIT License
Classifier: Programming Language :: Python
Classifier: Programming Language :: Python :: 3
Classifier: Programming Language :: Python :: 3.8
Classifier: Programming Language :: Python :: 3.9
Classifier: Programming Language :: Python :: 3.10
Classifier: Programming Language :: Python :: 3.11
Classifier: Programming Language :: Python :: 3.12
Classifier: Programming Language :: Python :: 3.13
Project-URL: Homepage, https://github.com/DavidPal/whitespace-format
Project-URL: Repository, https://github.com/DavidPal/whitespace-format
